{"users":[{"fullName":"cristiano","email":"felychk203@hotmail.com","password":"$2a$10$9C3YPOYFN3iso.LDKyonw.hPNeKXdfQc2A/gnmnH87SMAWck6DHGe"},{"fullName":"daniel cortes","email":"lucho234@hotmail.com","password":"$2a$10$.f1Zy9qHnb/E066wb1fw0eNorwovJO6FLm/4K6j/E9k5iF7OCVj1i"},{"fullName":"mauricio velez","email":"mauro12@hotmail.com","password":"$2a$10$RHQ1zOPI8IrkQZbkXrtP2.7iaZIX0nHUBBOj2WHL1UfaSoevnUtyK"},{"fullName":"carlos","email":"camilo2@hotmail.com","password":"$2a$10$ssPiq0uEBLclAtKU2HYUMeoflY9TfjhF6NMNAuWBtGUzeyb6KQQCa"}]}